[
  {
    "Id": 0,
    "thokNaath": "kuɔ̱ɔ̱t",
    "English": "cat"
  },
  {
    "Id": 1,
    "thokNaath": "rɔw",
    "English": "hippoptamus"
  },
  {
    "Id": 2,
    "thokNaath": "lony",
    "English": "lion" 
  },
  {
    "Id": 3,
    "thokNaath": "nyaŋ",
    "English": "crocodile"
  },
  {
    "Id": 4,
    "thokNaath": "tuaar",
    "English": "bee"
  },
  {
    "Id": 5,
    "thokNaath": "jio̱k",
    "English": "dog"  
  },
  {
    "Id": 6,
    "thokNaath": "kacik",
    "English": "donkey"  
  },
  {
    "Id": 7,
    "thokNaath": "guɔ̱r",
    "English": "elephant" 
  },
  {
    "Id": 8,
    "thokNaath": "diɛɛr",
    "English": "cricket" 
  },
  {
    "Id": 9,
    "thokNaath": "yew",
    "English": "catfish"
  },
  {
    "Id": 10,
    "thokNaath": "luth",
    "English": "mudfish"
  },
  {
    "Id": 11,
    "thokNaath": "riel",
    "English": "eel"
  },
  {
    "Id": 12,
    "thokNaath": "ti̱el",
    "English": "fish"
  },
  {
    "Id": 13,
    "thokNaath": "wuut",
    "English": "ostrich"
  },
  {
    "Id": 14,
    "thokNaath": "tuɔ̱t",
    "English": "goose"
  },
  {
    "Id": 15,
    "thokNaath": "miit",
    "English": "firefly"
  },
  {
    "Id": 16,
    "thokNaath": "manpalɛ̈k",
    "English": "hen"
  },
  {
    "Id": 17,
    "thokNaath": "käät",
    "English": "hawk"
  },
  {
    "Id": 18,
    "thokNaath": "guɛk",
    "English": "frog"
  },
  {
    "Id": 19,
    "thokNaath": "kerker",
    "English": "lizard"
  },
  {
    "Id": 20,
    "thokNaath": "",
    "English": ""
  }
]

